pyhavamal/__init__.py
pyhavamal/stanzas.py
pyhavamal/data/stanzas
pyhavamal-0.1.4.dist-info/LICENSE
pyhavamal-0.1.4.dist-info/METADATA
pyhavamal-0.1.4.dist-info/WHEEL
pyhavamal-0.1.4.dist-info/top_level.txt
pyhavamal-0.1.4.dist-info/RECORD
