Metadata-Version: 2.1
Name: pyhavamal
Version: 0.1.4
Summary: A CSV file containing the Old Norse Hávamál stanzas and a simple Python app for accessing them.
Home-page: https://github.com/equinlan/pyhavamal
Author: Evan Quinlan
Author-email: evan.quinlan@gmail.com
License: UNKNOWN
Platform: UNKNOWN
Classifier: Programming Language :: Python :: 3
Classifier: License :: OSI Approved :: MIT License
Classifier: Operating System :: OS Independent
Requires-Python: >=3.7
